LICENSE
MANIFEST.in
README.md
setup.cfg
setup.py
django_sendgrid_parse/__init__.py
django_sendgrid_parse/admin.py
django_sendgrid_parse/apps.py
django_sendgrid_parse/emails.py
django_sendgrid_parse/example.json
django_sendgrid_parse/forms.py
django_sendgrid_parse/models.py
django_sendgrid_parse/signals.py
django_sendgrid_parse/urls.py
django_sendgrid_parse/views.py
django_sendgrid_parse.egg-info/PKG-INFO
django_sendgrid_parse.egg-info/SOURCES.txt
django_sendgrid_parse.egg-info/dependency_links.txt
django_sendgrid_parse.egg-info/not-zip-safe
django_sendgrid_parse.egg-info/requires.txt
django_sendgrid_parse.egg-info/top_level.txt
django_sendgrid_parse/__pycache__/__init__.cpython-34.pyc
django_sendgrid_parse/__pycache__/admin.cpython-34.pyc
django_sendgrid_parse/__pycache__/apps.cpython-34.pyc
django_sendgrid_parse/__pycache__/emails.cpython-34.pyc
django_sendgrid_parse/__pycache__/models.cpython-34.pyc
django_sendgrid_parse/management/commands/__init__.py
django_sendgrid_parse/migrations/0001_initial.py
django_sendgrid_parse/migrations/0002_auto_20160729_1816.py
django_sendgrid_parse/migrations/0003_auto_20160730_0019.py
django_sendgrid_parse/migrations/0004_auto_20160816_1704.py
django_sendgrid_parse/migrations/0005_auto_20160816_1919.py
django_sendgrid_parse/migrations/0006_auto_20160816_2123.py
django_sendgrid_parse/migrations/0007_email_creation_date.py
django_sendgrid_parse/migrations/__init__.py
django_sendgrid_parse/migrations/__pycache__/0001_initial.cpython-34.pyc
django_sendgrid_parse/migrations/__pycache__/0002_auto_20160729_1816.cpython-34.pyc
django_sendgrid_parse/migrations/__pycache__/0003_auto_20160730_0019.cpython-34.pyc
django_sendgrid_parse/migrations/__pycache__/0004_auto_20160816_1704.cpython-34.pyc
django_sendgrid_parse/migrations/__pycache__/0005_auto_20160816_1919.cpython-34.pyc
django_sendgrid_parse/migrations/__pycache__/0006_auto_20160816_2123.cpython-34.pyc
django_sendgrid_parse/migrations/__pycache__/0007_email_creation_date.cpython-34.pyc
django_sendgrid_parse/migrations/__pycache__/__init__.cpython-34.pyc