Metadata-Version: 1.1
Name: django-sendgrid-parse
Version: 0.4.3
Summary: Django app to receive and save incoming emailnotification events from sendgrid to our database
Home-page: https://github.com/letops/django-sendgrid-parse
Author: GRVTYlabs
Author-email: daniel.ortiz@grvtylabs.com
License: MIT
Platform: UNKNOWN
Classifier: Development Status :: 3 - Alpha
Classifier: Environment :: Web Environment
Classifier: Intended Audience :: Developers
Classifier: License :: OSI Approved :: BSD License
Classifier: Operating System :: OS Independent
Classifier: Programming Language :: Python :: 3.2
Classifier: Programming Language :: Python :: 3.3
Classifier: Programming Language :: Python :: 3.4
Classifier: Framework :: Django
